nexus_extensibility/__init__.py
nexus_extensibility/_data_model.py
nexus_extensibility/_data_model_extensions.py
nexus_extensibility/_data_model_utilities.py
nexus_extensibility/_extensibility_data_source.py
nexus_extensibility/_extensibility_utilities.py
nexus_extensibility/_i_extension.py
nexus_extensibility-1.0.6.dist-info/METADATA
nexus_extensibility-1.0.6.dist-info/WHEEL
nexus_extensibility-1.0.6.dist-info/top_level.txt
nexus_extensibility-1.0.6.dist-info/RECORD
