Metadata-Version: 2.1
Name: nexus-extensibility
Version: 1.0.6
Summary: Type definitions to implement data sources for the Nexus system.
Home-page: https://github.com/malstroem-labs/nexus
Author: https://github.com/malstroem-labs
License: MIT
Project-URL: Project, https://malstroem-labs.github.io/Nexus
Project-URL: Repository, https://github.com/malstroem-labs/nexus
Keywords: Nexus extensibility time-series data lake
Platform: any
Classifier: Programming Language :: Python :: 3
Classifier: License :: OSI Approved :: MIT License
Classifier: Operating System :: OS Independent
Requires-Python: >=3.9
